{"0": "A06-8", "1": "A10-280", "2": "A11-26", "3": "A11-38", "4": "A11-40", "5": "A12-34", "6": "A13-1", "7": "A15-6", "8": "A16-1", "9": "A16-17", "10": "A16-2", "11": "A16-7", "12": "A99-2897", "13": "AKB3128", "14": "AKB3179", "15": "AKB3241", "16": "After Midnight", "17": "Amaze (NAI-14-133)", "18": "Aviator II (NAI-15-84)", "19": "BAR PP 71213", "20": "BAR PP 7236V", "21": "BAR PP 7309V", "22": "BAR PP 79366", "23": "BAR PP 79494", "24": "BAR PP 7K426", "25": "Babe", "26": "Barserati (BAR PP 110358)", "27": "Barvette HGT\u00ae", "28": "Blue Devil", "29": "Blue Gem (NAI-13-9)", "30": "Blue Knight", "31": "Bombay (GO-22B23)", "32": "Cloud (GO-2425)", "33": "Comanche (NAI-14-176)", "34": "DLFPS-340/3364", "35": "DLFPS-340/3438", "36": "DLFPS-340/3444", "37": "DLFPS-340/3446", "38": "DLFPS-340/3455", "39": "DLFPS-340/3494", "40": "DLFPS-340/3500", "41": "DLFPS-340/3548", "42": "DLFPS-340/3549", "43": "DLFPS-340/3550", "44": "DLFPS-340/3551", "45": "DLFPS-340/3552", "46": "DLFPS-340/3553", "47": "DLFPS-340/3556", "48": "Dublin (PST-K15-157)", "49": "Electric (PST-K11-118)", "50": "Finish Line (NAI-14-178)", "51": "Heartland (NAI-14-187)", "52": "J-1138", "53": "J-1319", "54": "J-2726", "55": "Jersey (NAI-A16-3)", "56": "KH3492", "57": "Kenblue", "58": "MVS-130", "59": "Midnight", "60": "NAI-14-122", "61": "NAI-14-128", "62": "NAI-14-132", "63": "NAI-15-80", "64": "NK-1", "65": "New Moon (PST-K15-177)", "66": "NuRush (J-3510)", "67": "Orion (PST-K13-143)", "68": "PPG-KB 1131", "69": "PPG-KB 1304", "70": "PPG-KB 1320", "71": "PST-11-7", "72": "PST-K13-141", "73": "PST-K15-167", "74": "PST-K15-172", "75": "PST-T14-39", "76": "Paloma (PST-K13-139)", "77": "Pivot", "78": "Prosperity", "79": "RAD 553", "80": "RAD-1776", "81": "Selway", "82": "Shamrock", "83": "Skye", "84": "Star (GO-2628)", "85": "Syrah (LTP-11-41)", "86": "Twilight (NAI-13-132)", "87": "United (NAI-13-14)", "88": "Yellowstone (A12-7)"}